kolibri/NLPDoc.py
kolibri/__init__.py
kolibri/box_link.py
kolibri/config.py
kolibri/config_copy.py
kolibri/document.py
kolibri/errors.py
kolibri/init_logger.py
kolibri/model.py
kolibri/modules.py
kolibri/nlp.py
kolibri/pipeComponent.py
kolibri/settings.py
kolibri/test_case.py
kolibri/upload_to_box.py
kolibri/version.py
kolibri/vocabulary.py
kolibri/classifier/__init__.py
kolibri/classifier/convnet.py
kolibri/classifier/httnet.py
kolibri/classifier/model.py
kolibri/classifier/models.py
kolibri/classifier/rnn.py
kolibri/classifier/sklearn_classifier.py
kolibri/classifier/cost_sensitive/__init__.py
kolibri/classifier/cost_sensitive/adacost.py
kolibri/classifier/dnn/__init__.py
kolibri/classifier/dnn/api.py
kolibri/classifier/dnn/bilstmcrf.py
kolibri/classifier/dnn/callbacks.py
kolibri/classifier/dnn/preprocessing.py
kolibri/classifier/dnn/utils.py
kolibri/classifier/ecoc/__init__.py
kolibri/classifier/ecoc/ecoc_classifier.py
kolibri/classifier/ecoc/matrix.py
kolibri/cluster/__init__.py
kolibri/cluster/baseTopic.py
kolibri/cluster/topics_lda.py
kolibri/data/__init__.py
kolibri/data/dataset.py
kolibri/data/document.py
kolibri/data/downloader.py
kolibri/data/idataset.py
kolibri/data/kolibri_data.py
kolibri/data/ressources.py
kolibri/data/training_data.py
kolibri/data/vocabulary.py
kolibri/data/writer_reader.py
kolibri/data/cleaner/__init__.py
kolibri/data/cleaner/email_.py
kolibri/data/cleaner/scripts/__init__.py
kolibri/data/cleaner/scripts/cleaning_scripts.py
kolibri/data/cleaner/scripts/email2text.py
kolibri/data/dataset_readers/__init__.py
kolibri/data/dataset_readers/dataset_reader.py
kolibri/data/dataset_readers/entity_reader_json.py
kolibri/data/dataset_readers/text_classification_json.py
kolibri/data/fields/__init__.py
kolibri/data/fields/field.py
kolibri/data/fields/label_field.py
kolibri/data/fields/list_field.py
kolibri/data/fields/sequence_field.py
kolibri/data/fields/sequence_label_field.py
kolibri/data/fields/text_field.py
kolibri/data/format/Csv.py
kolibri_nlp-1.1.73.dist-info/METADATA
kolibri_nlp-1.1.73.dist-info/WHEEL
kolibri_nlp-1.1.73.dist-info/top_level.txt
kolibri_nlp-1.1.73.dist-info/RECORD
