Metadata-Version: 2.1
Name: kolibri-nlp
Version: 1.1.73
Summary: An NLP toolkit
Home-page: UNKNOWN
Author: Mohamed Ben Haddou
Author-email: mbenhaddou@mentis.io
License: UNKNOWN
Platform: UNKNOWN
Classifier: Programming Language :: Python :: 3
Classifier: Operating System :: OS Independent
Requires-Python: >=3.6
